openchatbotclient/__init__.py
openchatbotclient/client.py
openchatbotclient/client_group.py
openchatbotclient/descriptor.py
openchatbotclient/exception.py
openchatbotclient/monitor.py
openchatbotclient/repository.py
openchatbotclient/response.py
openchatbotclient/response_group.py
openchatbotclient/test.py
open_chatbot_py_client-0.1.0.dist-info/LICENSE
open_chatbot_py_client-0.1.0.dist-info/METADATA
open_chatbot_py_client-0.1.0.dist-info/WHEEL
open_chatbot_py_client-0.1.0.dist-info/top_level.txt
open_chatbot_py_client-0.1.0.dist-info/RECORD
