Metadata-Version: 2.1
Name: open-chatbot-py-client
Version: 0.1.0
Summary: Client to access any chatbot compliant with the Alliance for Open Chatbot standard
Home-page: https://www.konverso.ai
Author: Konverso
Author-email: contact@konverso.ai
License: UNKNOWN
Platform: UNKNOWN
Classifier: Programming Language :: Python :: 3
Classifier: License :: OSI Approved :: MIT License
Classifier: Operating System :: OS Independent
Requires-Python: >=3.6
